{
  "main": {
    "id": "b9fd70b8d3d29db4",
    "type": "split",
    "children": [
      {
        "id": "cf5b01d41bce3a3a",
        "type": "tabs",
        "children": [
          {
            "id": "31238bbe10df5aad",
            "type": "leaf",
            "pinned": true,
            "state": {
              "type": "markdown",
              "state": {
                "file": "Plan/Đọc sách.md",
                "mode": "source",
                "backlinks": false,
                "source": false
              },
              "pinned": true
            }
          },
          {
            "id": "4277d530ef41965a",
            "type": "leaf",
            "pinned": true,
            "state": {
              "type": "markdown",
              "state": {
                "file": "Đang làm dở dang.md",
                "mode": "source",
                "backlinks": false,
                "source": false
              },
              "pinned": true
            }
          },
          {
            "id": "23cd98d3f5ef91ba",
            "type": "leaf",
            "state": {
              "type": "markdown",
              "state": {
                "file": "Books/Dive Into Design Pattern/III. Software Design Principles/SOLID Principles/5. Dependency Inversion Principle.md",
                "mode": "source",
                "backlinks": false,
                "source": false
              }
            }
          }
        ],
        "currentTab": 2
      }
    ],
    "direction": "vertical"
  },
  "left": {
    "id": "66cc03a3cc2fc7ee",
    "type": "split",
    "children": [
      {
        "id": "a4387824724a1d0d",
        "type": "tabs",
        "children": [
          {
            "id": "e9e879b4f5a74a3d",
            "type": "leaf",
            "state": {
              "type": "file-explorer",
              "state": {
                "sortOrder": "alphabetical"
              }
            }
          },
          {
            "id": "b79a319d5e640948",
            "type": "leaf",
            "state": {
              "type": "search",
              "state": {
                "query": "github",
                "matchingCase": false,
                "explainSearch": false,
                "collapseAll": false,
                "extraContext": false,
                "sortOrder": "alphabetical"
              }
            }
          },
          {
            "id": "88beac909926e7f1",
            "type": "leaf",
            "state": {
              "type": "bookmarks",
              "state": {}
            }
          }
        ]
      }
    ],
    "direction": "horizontal",
    "width": 339.5
  },
  "right": {
    "id": "337706b808fe28a1",
    "type": "split",
    "children": [
      {
        "id": "b798dfb612760b9b",
        "type": "tabs",
        "children": [
          {
            "id": "e26c17319e1ffcaa",
            "type": "leaf",
            "state": {
              "type": "tag",
              "state": {
                "sortOrder": "alphabetical",
                "useHierarchy": true
              }
            }
          },
          {
            "id": "5ebaf0685a496f41",
            "type": "leaf",
            "state": {
              "type": "backlink",
              "state": {
                "file": "Books/Dive Into Design Pattern/III. Software Design Principles/SOLID Principles/5. Dependency Inversion Principle.md",
                "collapseAll": false,
                "extraContext": false,
                "sortOrder": "alphabetical",
                "showSearch": false,
                "searchQuery": "",
                "backlinkCollapsed": false,
                "unlinkedCollapsed": true
              }
            }
          },
          {
            "id": "d682489f9144bc5b",
            "type": "leaf",
            "state": {
              "type": "outline",
              "state": {
                "file": "Books/Dive Into Design Pattern/III. Software Design Principles/SOLID Principles/5. Dependency Inversion Principle.md"
              }
            }
          },
          {
            "id": "5385b8b0765a3335",
            "type": "leaf",
            "state": {
              "type": "all-properties",
              "state": {
                "sortOrder": "frequency",
                "showSearch": false,
                "searchQuery": ""
              }
            }
          }
        ]
      }
    ],
    "direction": "horizontal",
    "width": 200,
    "collapsed": true
  },
  "left-ribbon": {
    "hiddenItems": {
      "switcher:Open quick switcher": false,
      "workspaces:Manage workspace layouts": false,
      "templates:Insert template": false,
      "canvas:Create new canvas": false,
      "command-palette:Open command palette": false,
      "graph:Open graph view": false,
      "publish:Publish changes...": false
    }
  },
  "active": "23cd98d3f5ef91ba",
  "lastOpenFiles": [
    "Knowledge/Developer/Fundamentals/Principles/SOLID Principles.md",
    "Books/Dive Into Design Pattern/III. Software Design Principles/SOLID Principles/5. Dependency Inversion Principle.md",
    "Plan/Đọc sách.md",
    "Books/Dive Into Design Pattern/III. Software Design Principles/SOLID Principles/4. Interface Segregation Principle.md",
    "Images/BOOKS/oop-27.png",
    "Images/BOOKS/oop-26.png",
    "Images/BOOKS/Screenshot from 2024-03-14 21-09-56.png",
    "Images/BOOKS/Screenshot from 2024-03-14 21-11-52.png",
    "Books/Dive Into Design Pattern/III. Software Design Principles/SOLID Principles/3. Liskov Substitution Principle.md",
    "Books/Dive Into Design Pattern/I. Intro to OOP/Relations Between Objects.md",
    "Images/BOOKS/oop-25.png",
    "Images/BOOKS/oop-24.png",
    "Images/BOOKS/Screenshot from 2024-03-14 14-40-53.png",
    "Images/BOOKS/Screenshot from 2024-03-14 14-41-07.png",
    "Books/Dive Into Design Pattern/Catalog.md",
    "Đang làm dở dang.md",
    "Knowledge/English/Videos/Video 1.md",
    "Books/Dive Into Design Pattern/III. Software Design Principles/SOLID Principles/2. Open&Close Principle.md",
    "Books/Dive Into Design Pattern/III. Software Design Principles/SOLID Principles/1. Single reponsibility Principle.md",
    "Images/BOOKS/oop-23.png",
    "Images/BOOKS/oop-22.png",
    "Books/Dive Into Design Pattern/II. Intro to Desiign Patterns/Introduce about Design pattern.md",
    "Books/Dive Into Design Pattern/III. Software Design Principles/SOLID Principles/Untitled",
    "Books/Dive Into Design Pattern/III. Software Design Principles/SOLID Principles",
    "Books/Dive Into Design Pattern/II. Intro to Desiign Patterns",
    "Books/Dive Into Design Pattern/III. Software Design Principles",
    "Books/Dive Into Design Pattern/I. Intro to OOP",
    "Books/Dive Into Design Pattern/III. Software Design Principles/Design Principles/3. Favor Composition Over Inheritance.md",
    "Books/Dive Into Design Pattern/III. Software Design Principles/Design Principles/1. Encapsulate What Varies.md",
    "Books/Dive Into Design Pattern/III. Software Design Principles/Design Principles/2. Program to an Interface, not an Implementation.md",
    "Knowledge/Developer/Git/Basic Commands.md",
    "Knowledge/Telegram Tips.md",
    "Books/Dive Into Design Pattern/III. Software Design Principles/Design Principles",
    "Books/Dive Into Design Pattern/III. Software Design Principles/Features of Good Design.md",
    "Knowledge/Developer/Git/Introduction.md",
    "Knowledge/Markdown.md",
    "Knowledge/Developer/Git",
    "References/Golang.md",
    "References/Youtube.md",
    "Knowledge/Developer/Internet/Internet.md",
    "Knowledge/Developer/Internet",
    "Knowledge/Developer/internet 2.md",
    "Knowledge/Linux-Command.md",
    "Knowledge/English/Dách sách.md",
    "Knowledge/English/Videos",
    "Knowledge/English/[English (auto-generated)] My Kitchen _ Improve Your English _ English Listening Skills - Speaking Skills _ Cooking [DownSub.com].txt",
    "Projects/FINVIET/Backend/Forgot Password.canvas",
    "Projects/FINVIET/Eco Game/LuckyWheel/Untitled.canvas",
    "Untitled.canvas",
    "Untitled 1.canvas",
    "Untitled 2.canvas",
    "Projects/FINVIET/Eco Game/LuckyWheel/lucky-wheek-func-flow.canvas",
    "Projects/FINVIET/Eco Web App/Flow Thanh toán.canvas",
    "Projects/FINVIET/Eco Web App/Flow Cash.canvas",
    "Projects/FINVIET/Eco Game/Sync-UserGame.canvas",
    "PERSONAL/Projects/FINVIET/Eco Game/LuckyWheel/lucky-wheek-func-flow.canvas"
  ]
}